[
  {
    "name": "Citronix",
    "desc": "Citronix is a farm management system, developed using Spring Boot, designed to optimize lemon production, harvest, and sales.",
    "image": "flipkartmern",
    "category": "mern",
    "links": {
      "code": "https://github.com/J-Maryam/Citronix"
    }
  },
  {
    "name": "YouQuiz",
    "desc": "YouQuiz is a Spring Boot app for managing quizzes and exams.",
    "image": "flipkartmern",
    "category": "mern",
    "links": {
      "code": "https://github.com/J-Maryam/YouQuiz"
    }
  },
  {
    "name": "WaitingRoom",
    "desc": "WRM is a REST API for managing waiting rooms and organizing visitor flows in offices, services, or businesses.",
    "image": "resumegen",
    "category": "mern",
    "links": {
      "code": "https://github.com/J-Maryam/WaitingRoom"
    }
  },
  {
    "name": "E-Banking",
    "desc": "E-Banking is a REST API with Spring Security, offering role-based access and user management.",
    "image": "reactprojects",
    "category": "mern",
    "links": {
      "code": "https://github.com/J-Maryam/eBanking"
    }
  },
  {
    "name": "ITLens",
    "desc": "ITLens is a REST API for managing IT surveys, enabling survey creation, response collection, and real-time analysis.",
    "image": "flipkartphp",
    "category": "lamp",
    "links": {
      "code": "https://github.com/J-Maryam/ITLens"
    }
  },
  {
    "name": "Bati-Cuisine",
    "desc": "Bati-Cuisine is a Java app for estimating construction and renovation costs.",
    "image": "jspro",
    "category": "basicweb",
    "links": {
      "code": "https://github.com/J-Maryam/Bati-Cuisine"
    }
  }
  ]
